vlute_faces_services/__init__.py
vlute_faces_services/call.py
vlute_faces_services/faces.py
vlute_faces_services/qllb.py
vlute_faces_services/speech.py
vlute_faces_services-0.0.3.dist-info/METADATA
vlute_faces_services-0.0.3.dist-info/WHEEL
vlute_faces_services-0.0.3.dist-info/top_level.txt
vlute_faces_services-0.0.3.dist-info/RECORD
