Metadata-Version: 2.1
Name: vlute-faces-services
Version: 0.0.3
Summary: UNKNOWN
Home-page: http://fit.vlute.edu.vn
Author: truongtpa
Author-email: truongtpa@vlute.edu.vn
License: MIT
Platform: UNKNOWN
Requires-Dist: certifi (==2020.12.5)
Requires-Dist: chardet (==4.0.0)
Requires-Dist: click (==7.1.2)
Requires-Dist: gTTS (==2.2.2)
Requires-Dist: idna (==2.10)
Requires-Dist: playsound (==1.2.2)
Requires-Dist: requests (==2.25.1)
Requires-Dist: six (==1.15.0)
Requires-Dist: urllib3 (==1.26.3)
